example_python_package_intern_pyspack/__init__.py
example_python_package_intern_pyspack/utils.py
example_python_package_intern_pyspack-0.1.5.dist-info/WHEEL
example_python_package_intern_pyspack-0.1.5.dist-info/METADATA
example_python_package_intern_pyspack-0.1.5.dist-info/RECORD
