Metadata-Version: 2.1
Name: example_python_package_intern_pyspack
Version: 0.1.5
Summary: An example pure-python package
Author-email: David Hofer <davhofer@ethz.ch>
Requires-Python: >=3.8
Classifier: Programming Language :: Python :: 3
Classifier: License :: OSI Approved :: MIT License
Classifier: Operating System :: OS Independent
